<tv>
<channel id="ppv-12972">
<display-name>Getafe CF vs. Girona FC</display-name>
</channel>
<programme
start="20251031200000 +0000"
stop="20251031223000 +0000"
channel="ppv-12972"
>
<title lang="en">Getafe CF vs. Girona FC</title>
<sub-title>Football</sub-title>
<video>
<present>yes</present>
<colour>yes</colour>
</video>
<audio>
<present>yes</present>
<stereo>stereo</stereo>
</audio>
<category>Football</category>
<icon src="https://ppv.to/assets/thumb/546c12ae47c6054e2004e5982cbcfa32-thumbnail.jpg" />
</programme>

<channel id="ppv-12897">
<display-name>Augsburg vs. Dortmund</display-name>
</channel>
<programme
start="20251031193000 +0000"
stop="20251031220000 +0000"
channel="ppv-12897"
>
<title lang="en">Augsburg vs. Dortmund</title>
<sub-title>Football</sub-title>
<video>
<present>yes</present>
<colour>yes</colour>
</video>
<audio>
<present>yes</present>
<stereo>stereo</stereo>
</audio>
<category>Football</category>
<icon src="https://ppv.to/assets/thumb/24d7a31ee510df81acf05b3210e082d2-thumbnail.jpg" />
</programme>

<channel id="ppv-12915">
<display-name>Pisa vs. Lazio</display-name>
</channel>
<programme
start="20251030194500 +0000"
stop="20251030221500 +0000"
channel="ppv-12915"
>
<title lang="en">Pisa vs. Lazio</title>
<sub-title>Football</sub-title>
<video>
<present>yes</present>
<colour>yes</colour>
</video>
<audio>
<present>yes</present>
<stereo>stereo</stereo>
</audio>
<category>Football</category>
<icon src="https://ppv.to/assets/thumb/335be3c4ce408fcb45138d4eae416c77-thumbnail.jpg" />
</programme>

<channel id="ppv-12914">
<display-name>Cagliari vs. Sassuolo</display-name>
</channel>
<programme
start="20251030173000 +0000"
stop="20251030200000 +0000"
channel="ppv-12914"
>
<title lang="en">Cagliari vs. Sassuolo</title>
<sub-title>Football</sub-title>
<video>
<present>yes</present>
<colour>yes</colour>
</video>
<audio>
<present>yes</present>
<stereo>stereo</stereo>
</audio>
<category>Football</category>
<icon src="https://ppv.to/assets/thumb/81b7504afe264c1c2f21da02571cd2c7-thumbnail.jpg" />
</programme>

<channel id="ppv-12885">
<display-name>WWE: Friday Night Smackdown</display-name>
</channel>
<programme
start="20251101000000 +0000"
stop="20251101030000 +0000"
channel="ppv-12885"
>
<title lang="en">WWE: Friday Night Smackdown</title>
<sub-title>Wrestling</sub-title>
<video>
<present>yes</present>
<colour>yes</colour>
</video>
<audio>
<present>yes</present>
<stereo>stereo</stereo>
</audio>
<category>Wrestling</category>
<icon src="https://ppv.to/assets/thumb/ec7810b68fc39115ce3510bcf9687a63-thumbnail.jpg" />
</programme>

<channel id="ppv-12884">
<display-name>TNA: Impact</display-name>
</channel>
<programme
start="20251031000000 +0000"
stop="20251031030000 +0000"
channel="ppv-12884"
>
<title lang="en">TNA: Impact</title>
<sub-title>Wrestling</sub-title>
<video>
<present>yes</present>
<colour>yes</colour>
</video>
<audio>
<present>yes</present>
<stereo>stereo</stereo>
</audio>
<category>Wrestling</category>
<icon src="https://ppv.to/assets/thumb/78f581ee61589a76f6bcdeb095f95c12-thumbnail.jpg" />
</programme>
</tv>