<tv>
<channel id="ppv-12995">
<display-name>Seattle Seahawks vs. Washington Commanders</display-name>
</channel>
<programme
start="20251103022000 +0000"
stop="20251103055000 +0000"
channel="ppv-12995"
>
<title lang="en">Seattle Seahawks vs. Washington Commanders</title>
<sub-title>American Football</sub-title>
<video>
<present>yes</present>
<colour>yes</colour>
</video>
<audio>
<present>yes</present>
<stereo>stereo</stereo>
</audio>
<category>American Football</category>
<icon src="https://api.ppvs.su/assets/thumb/4968e95559653bf4626b892c1180e0a0-thumbnail.jpg" />
</programme>

<channel id="ppv-12994">
<display-name>Kansas City Chiefs vs. Buffalo Bills</display-name>
</channel>
<programme
start="20251102222500 +0000"
stop="20251103015500 +0000"
channel="ppv-12994"
>
<title lang="en">Kansas City Chiefs vs. Buffalo Bills</title>
<sub-title>American Football</sub-title>
<video>
<present>yes</present>
<colour>yes</colour>
</video>
<audio>
<present>yes</present>
<stereo>stereo</stereo>
</audio>
<category>American Football</category>
<icon src="https://api.ppvs.su/assets/thumb/ffd2d09e713ca1b1c09e17c13e22d73b-thumbnail.jpg" />
</programme>

<channel id="ppv-12992">
<display-name>Jacksonville Jaguars vs. Las Vegas Raiders</display-name>
</channel>
<programme
start="20251102220500 +0000"
stop="20251103013500 +0000"
channel="ppv-12992"
>
<title lang="en">Jacksonville Jaguars vs. Las Vegas Raiders</title>
<sub-title>American Football</sub-title>
<video>
<present>yes</present>
<colour>yes</colour>
</video>
<audio>
<present>yes</present>
<stereo>stereo</stereo>
</audio>
<category>American Football</category>
<icon src="https://api.ppvs.su/assets/thumb/8059360e4572a5bb4933d84ff7a674cf-thumbnail.jpg" />
</programme>

<channel id="ppv-12993">
<display-name>New Orleans Saints vs. Los Angeles Rams</display-name>
</channel>
<programme
start="20251102220500 +0000"
stop="20251103013500 +0000"
channel="ppv-12993"
>
<title lang="en">New Orleans Saints vs. Los Angeles Rams</title>
<sub-title>American Football</sub-title>
<video>
<present>yes</present>
<colour>yes</colour>
</video>
<audio>
<present>yes</present>
<stereo>stereo</stereo>
</audio>
<category>American Football</category>
<icon src="https://api.ppvs.su/assets/thumb/61395b09ec7e128d3cb722b2621f3d93-thumbnail.jpg" />
</programme>

<channel id="ppv-12984">
<display-name>Chicago Bears vs. Cincinnati Bengals</display-name>
</channel>
<programme
start="20251102190000 +0000"
stop="20251102223000 +0000"
channel="ppv-12984"
>
<title lang="en">Chicago Bears vs. Cincinnati Bengals</title>
<sub-title>American Football</sub-title>
<video>
<present>yes</present>
<colour>yes</colour>
</video>
<audio>
<present>yes</present>
<stereo>stereo</stereo>
</audio>
<category>American Football</category>
<icon src="https://api.ppvs.su/assets/thumb/d899fac9d8c6411bfcf573dd3fac27f0-thumbnail.jpg" />
</programme>

<channel id="ppv-12985">
<display-name>Minnesota Vikings vs. Detroit Lions</display-name>
</channel>
<programme
start="20251102190000 +0000"
stop="20251102223000 +0000"
channel="ppv-12985"
>
<title lang="en">Minnesota Vikings vs. Detroit Lions</title>
<sub-title>American Football</sub-title>
<video>
<present>yes</present>
<colour>yes</colour>
</video>
<audio>
<present>yes</present>
<stereo>stereo</stereo>
</audio>
<category>American Football</category>
<icon src="https://api.ppvs.su/assets/thumb/e3491071d59a937b29990e7325ffc4dd-thumbnail.jpg" />
</programme>

<channel id="ppv-12986">
<display-name>Carolina Panthers vs. Green Bay Packers</display-name>
</channel>
<programme
start="20251102190000 +0000"
stop="20251102223000 +0000"
channel="ppv-12986"
>
<title lang="en">Carolina Panthers vs. Green Bay Packers</title>
<sub-title>American Football</sub-title>
<video>
<present>yes</present>
<colour>yes</colour>
</video>
<audio>
<present>yes</present>
<stereo>stereo</stereo>
</audio>
<category>American Football</category>
<icon src="https://api.ppvs.su/assets/thumb/4214ffe042682b9bb4beaf0a821dcbb9-thumbnail.jpg" />
</programme>

<channel id="ppv-12987">
<display-name>Los Angeles Chargers vs. Tennessee Titans</display-name>
</channel>
<programme
start="20251102190000 +0000"
stop="20251102223000 +0000"
channel="ppv-12987"
>
<title lang="en">Los Angeles Chargers vs. Tennessee Titans</title>
<sub-title>American Football</sub-title>
<video>
<present>yes</present>
<colour>yes</colour>
</video>
<audio>
<present>yes</present>
<stereo>stereo</stereo>
</audio>
<category>American Football</category>
<icon src="https://api.ppvs.su/assets/thumb/69bb6cb648333c874aa48fb5bbe06566-thumbnail.jpg" />
</programme>

<channel id="ppv-12988">
<display-name>Atlanta Falcons vs. New England Patriots</display-name>
</channel>
<programme
start="20251102190000 +0000"
stop="20251102223000 +0000"
channel="ppv-12988"
>
<title lang="en">Atlanta Falcons vs. New England Patriots</title>
<sub-title>American Football</sub-title>
<video>
<present>yes</present>
<colour>yes</colour>
</video>
<audio>
<present>yes</present>
<stereo>stereo</stereo>
</audio>
<category>American Football</category>
<icon src="https://api.ppvs.su/assets/thumb/79cfc99f7a38f5a2e47b24edd5513f3d-thumbnail.jpg" />
</programme>

<channel id="ppv-12989">
<display-name>San Francisco 49ers vs. New York Giants</display-name>
</channel>
<programme
start="20251102190000 +0000"
stop="20251102223000 +0000"
channel="ppv-12989"
>
<title lang="en">San Francisco 49ers vs. New York Giants</title>
<sub-title>American Football</sub-title>
<video>
<present>yes</present>
<colour>yes</colour>
</video>
<audio>
<present>yes</present>
<stereo>stereo</stereo>
</audio>
<category>American Football</category>
<icon src="https://api.ppvs.su/assets/thumb/bba960ac38e68a1d539ced522297804b-thumbnail.jpg" />
</programme>

<channel id="ppv-12990">
<display-name>Indianapolis Colts vs. Pittsburgh Steelers</display-name>
</channel>
<programme
start="20251102190000 +0000"
stop="20251102223000 +0000"
channel="ppv-12990"
>
<title lang="en">Indianapolis Colts vs. Pittsburgh Steelers</title>
<sub-title>American Football</sub-title>
<video>
<present>yes</present>
<colour>yes</colour>
</video>
<audio>
<present>yes</present>
<stereo>stereo</stereo>
</audio>
<category>American Football</category>
<icon src="https://api.ppvs.su/assets/thumb/32c0fb0c77e9aaa6b192674632bf3bb5-thumbnail.jpg" />
</programme>

<channel id="ppv-12991">
<display-name>Denver Broncos vs. Houston Texans</display-name>
</channel>
<programme
start="20251102190000 +0000"
stop="20251102223000 +0000"
channel="ppv-12991"
>
<title lang="en">Denver Broncos vs. Houston Texans</title>
<sub-title>American Football</sub-title>
<video>
<present>yes</present>
<colour>yes</colour>
</video>
<audio>
<present>yes</present>
<stereo>stereo</stereo>
</audio>
<category>American Football</category>
<icon src="https://api.ppvs.su/assets/thumb/3047eb139c3d1ae607a170ca7eef9dba-thumbnail.jpg" />
</programme>

<channel id="ppv-13061">
<display-name>Cincinnati Bearcats vs. Utah Utes</display-name>
</channel>
<programme
start="20251102031500 +0000"
stop="20251102064500 +0000"
channel="ppv-13061"
>
<title lang="en">Cincinnati Bearcats vs. Utah Utes</title>
<sub-title>American Football</sub-title>
<video>
<present>yes</present>
<colour>yes</colour>
</video>
<audio>
<present>yes</present>
<stereo>stereo</stereo>
</audio>
<category>American Football</category>
<icon src="https://api.ppvs.su/assets/thumb/dd2a828f06f06e830811785886ea6eb3-thumbnail.jpg" />
</programme>

<channel id="ppv-13058">
<display-name>Georgia Tech Yellow Jackets vs. NC State Wolfpack</display-name>
</channel>
<programme
start="20251101233000 +0000"
stop="20251102030000 +0000"
channel="ppv-13058"
>
<title lang="en">Georgia Tech Yellow Jackets vs. NC State Wolfpack</title>
<sub-title>American Football</sub-title>
<video>
<present>yes</present>
<colour>yes</colour>
</video>
<audio>
<present>yes</present>
<stereo>stereo</stereo>
</audio>
<category>American Football</category>
<icon src="https://api.ppvs.su/assets/thumb/678b41fc1c9d323a75d980f53a7c15d0-thumbnail.jpg" />
</programme>

<channel id="ppv-13059">
<display-name>Oklahoma Sooners vs. Tennessee Volunteers</display-name>
</channel>
<programme
start="20251101233000 +0000"
stop="20251102030000 +0000"
channel="ppv-13059"
>
<title lang="en">Oklahoma Sooners vs. Tennessee Volunteers</title>
<sub-title>American Football</sub-title>
<video>
<present>yes</present>
<colour>yes</colour>
</video>
<audio>
<present>yes</present>
<stereo>stereo</stereo>
</audio>
<category>American Football</category>
<icon src="https://api.ppvs.su/assets/thumb/0b1c951d8c7d8412393251945e2fddd1-thumbnail.jpg" />
</programme>

<channel id="ppv-13060">
<display-name>USC Trojans vs. Nebraska Cornhuskers</display-name>
</channel>
<programme
start="20251101233000 +0000"
stop="20251102030000 +0000"
channel="ppv-13060"
>
<title lang="en">USC Trojans vs. Nebraska Cornhuskers</title>
<sub-title>American Football</sub-title>
<video>
<present>yes</present>
<colour>yes</colour>
</video>
<audio>
<present>yes</present>
<stereo>stereo</stereo>
</audio>
<category>American Football</category>
<icon src="https://api.ppvs.su/assets/thumb/8da3e2a7674f9e2239eae845a8ff9c01-thumbnail.jpg" />
</programme>

<channel id="ppv-13056">
<display-name>South Carolina Gamecocks vs. Ole Miss Rebels</display-name>
</channel>
<programme
start="20251101230000 +0000"
stop="20251102023000 +0000"
channel="ppv-13056"
>
<title lang="en">South Carolina Gamecocks vs. Ole Miss Rebels</title>
<sub-title>American Football</sub-title>
<video>
<present>yes</present>
<colour>yes</colour>
</video>
<audio>
<present>yes</present>
<stereo>stereo</stereo>
</audio>
<category>American Football</category>
<icon src="https://api.ppvs.su/assets/thumb/1a9505e0d34113d28a08b4ba0570e5bf-thumbnail.jpg" />
</programme>

<channel id="ppv-13057">
<display-name>Purdue Boilermakers vs. Michigan Wolverines</display-name>
</channel>
<programme
start="20251101230000 +0000"
stop="20251102023000 +0000"
channel="ppv-13057"
>
<title lang="en">Purdue Boilermakers vs. Michigan Wolverines</title>
<sub-title>American Football</sub-title>
<video>
<present>yes</present>
<colour>yes</colour>
</video>
<audio>
<present>yes</present>
<stereo>stereo</stereo>
</audio>
<category>American Football</category>
<icon src="https://api.ppvs.su/assets/thumb/ebd1643b353e50572da3b95013b8e2d0-thumbnail.jpg" />
</programme>

<channel id="ppv-13055">
<display-name>Virginia Cavaliers vs. California Golden Bears</display-name>
</channel>
<programme
start="20251101194500 +0000"
stop="20251101231500 +0000"
channel="ppv-13055"
>
<title lang="en">Virginia Cavaliers vs. California Golden Bears</title>
<sub-title>American Football</sub-title>
<video>
<present>yes</present>
<colour>yes</colour>
</video>
<audio>
<present>yes</present>
<stereo>stereo</stereo>
</audio>
<category>American Football</category>
<icon src="https://api.ppvs.su/assets/thumb/791f5f17b826c0e945ca09882cea7058-thumbnail.jpg" />
</programme>

<channel id="ppv-13051">
<display-name>Indiana Hoosiers vs. Maryland Terrapins</display-name>
</channel>
<programme
start="20251101193000 +0000"
stop="20251101230000 +0000"
channel="ppv-13051"
>
<title lang="en">Indiana Hoosiers vs. Maryland Terrapins</title>
<sub-title>American Football</sub-title>
<video>
<present>yes</present>
<colour>yes</colour>
</video>
<audio>
<present>yes</present>
<stereo>stereo</stereo>
</audio>
<category>American Football</category>
<icon src="https://api.ppvs.su/assets/thumb/bfb6d9a9c6ef7a84bfcc3a6f06e43291-thumbnail.jpg" />
</programme>

<channel id="ppv-13052">
<display-name>Georgia Bulldogs vs. Florida Gators</display-name>
</channel>
<programme
start="20251101193000 +0000"
stop="20251101230000 +0000"
channel="ppv-13052"
>
<title lang="en">Georgia Bulldogs vs. Florida Gators</title>
<sub-title>American Football</sub-title>
<video>
<present>yes</present>
<colour>yes</colour>
</video>
<audio>
<present>yes</present>
<stereo>stereo</stereo>
</audio>
<category>American Football</category>
<icon src="https://api.ppvs.su/assets/thumb/232d1f4b48ed9ffa31ce5edf4fb3e578-thumbnail.jpg" />
</programme>

<channel id="ppv-13053">
<display-name>Notre Dame Fighting Irish vs. Boston College Eagles</display-name>
</channel>
<programme
start="20251101193000 +0000"
stop="20251101230000 +0000"
channel="ppv-13053"
>
<title lang="en">Notre Dame Fighting Irish vs. Boston College Eagles</title>
<sub-title>American Football</sub-title>
<video>
<present>yes</present>
<colour>yes</colour>
</video>
<audio>
<present>yes</present>
<stereo>stereo</stereo>
</audio>
<category>American Football</category>
<icon src="https://api.ppvs.su/assets/thumb/df94532d2cb0d3e80f8b9e46fbabe76f-thumbnail.jpg" />
</programme>

<channel id="ppv-13054">
<display-name>Texas Tech Red Raiders vs. Kansas State Wildcats</display-name>
</channel>
<programme
start="20251101193000 +0000"
stop="20251101230000 +0000"
channel="ppv-13054"
>
<title lang="en">Texas Tech Red Raiders vs. Kansas State Wildcats</title>
<sub-title>American Football</sub-title>
<video>
<present>yes</present>
<colour>yes</colour>
</video>
<audio>
<present>yes</present>
<stereo>stereo</stereo>
</audio>
<category>American Football</category>
<icon src="https://api.ppvs.su/assets/thumb/17804e17815994065895955b55bdc0c7-thumbnail.jpg" />
</programme>

<channel id="ppv-13050">
<display-name>Louisville Cardinals vs. Virginia Tech Hokies</display-name>
</channel>
<programme
start="20251101190000 +0000"
stop="20251101223000 +0000"
channel="ppv-13050"
>
<title lang="en">Louisville Cardinals vs. Virginia Tech Hokies</title>
<sub-title>American Football</sub-title>
<video>
<present>yes</present>
<colour>yes</colour>
</video>
<audio>
<present>yes</present>
<stereo>stereo</stereo>
</audio>
<category>American Football</category>
<icon src="https://api.ppvs.su/assets/thumb/58f583ac1d97d7b128bd858874509324-thumbnail.jpg" />
</programme>

<channel id="ppv-13065">
<display-name>Los Angeles Dodgers vs. Toronto Blue Jays</display-name>
</channel>
<programme
start="20251102000000 +0000"
stop="20251102030000 +0000"
channel="ppv-13065"
>
<title lang="en">Los Angeles Dodgers vs. Toronto Blue Jays</title>
<sub-title>Baseball</sub-title>
<video>
<present>yes</present>
<colour>yes</colour>
</video>
<audio>
<present>yes</present>
<stereo>stereo</stereo>
</audio>
<category>Baseball</category>
<icon src="https://api.ppvs.su/assets/thumb/fa14655fefa2fb97929805b7618da2bd-thumbnail.jpg" />
</programme>

<channel id="ppv-13068">
<display-name>Dallas Mavericks vs. Detroit Pistons</display-name>
</channel>
<programme
start="20251102020000 +0000"
stop="20251102044800 +0000"
channel="ppv-13068"
>
<title lang="en">Dallas Mavericks vs. Detroit Pistons</title>
<sub-title>Basketball</sub-title>
<video>
<present>yes</present>
<colour>yes</colour>
</video>
<audio>
<present>yes</present>
<stereo>stereo</stereo>
</audio>
<category>Basketball</category>
<icon src="https://api.ppvs.su/assets/thumb/4203ea065115fd80f15d7cb4935b41d7-thumbnail.jpg" />
</programme>

<channel id="ppv-13067">
<display-name>Houston Rockets vs. Boston Celtics</display-name>
</channel>
<programme
start="20251102000000 +0000"
stop="20251102024800 +0000"
channel="ppv-13067"
>
<title lang="en">Houston Rockets vs. Boston Celtics</title>
<sub-title>Basketball</sub-title>
<video>
<present>yes</present>
<colour>yes</colour>
</video>
<audio>
<present>yes</present>
<stereo>stereo</stereo>
</audio>
<category>Basketball</category>
<icon src="https://api.ppvs.su/assets/thumb/fcc921cef68a69f25073001b0709460e-thumbnail.jpg" />
</programme>

<channel id="ppv-13064">
<display-name>Golden State Warriors vs. Indiana Pacers</display-name>
</channel>
<programme
start="20251101230000 +0000"
stop="20251102014800 +0000"
channel="ppv-13064"
>
<title lang="en">Golden State Warriors vs. Indiana Pacers</title>
<sub-title>Basketball</sub-title>
<video>
<present>yes</present>
<colour>yes</colour>
</video>
<audio>
<present>yes</present>
<stereo>stereo</stereo>
</audio>
<category>Basketball</category>
<icon src="https://api.ppvs.su/assets/thumb/ced09623b9d799722764eef4ac50d935-thumbnail.jpg" />
</programme>

<channel id="ppv-13066">
<display-name>Orlando Magic vs. Washington Wizards</display-name>
</channel>
<programme
start="20251101230000 +0000"
stop="20251102014800 +0000"
channel="ppv-13066"
>
<title lang="en">Orlando Magic vs. Washington Wizards</title>
<sub-title>Basketball</sub-title>
<video>
<present>yes</present>
<colour>yes</colour>
</video>
<audio>
<present>yes</present>
<stereo>stereo</stereo>
</audio>
<category>Basketball</category>
<icon src="https://api.ppvs.su/assets/thumb/5fae1c16aae5dd01f7217315ddf307aa-thumbnail.jpg" />
</programme>

<channel id="ppv-13063">
<display-name>Minnesota Timberwolves vs. Charlotte Hornets</display-name>
</channel>
<programme
start="20251101220000 +0000"
stop="20251102004800 +0000"
channel="ppv-13063"
>
<title lang="en">Minnesota Timberwolves vs. Charlotte Hornets</title>
<sub-title>Basketball</sub-title>
<video>
<present>yes</present>
<colour>yes</colour>
</video>
<audio>
<present>yes</present>
<stereo>stereo</stereo>
</audio>
<category>Basketball</category>
<icon src="https://api.ppvs.su/assets/thumb/f782b5c9c87a64b6e4fa325086315f4d-thumbnail.jpg" />
</programme>

<channel id="ppv-13062">
<display-name>Sacramento Kings vs. Milwaukee Bucks</display-name>
</channel>
<programme
start="20251101210000 +0000"
stop="20251101234800 +0000"
channel="ppv-13062"
>
<title lang="en">Sacramento Kings vs. Milwaukee Bucks</title>
<sub-title>Basketball</sub-title>
<video>
<present>yes</present>
<colour>yes</colour>
</video>
<audio>
<present>yes</present>
<stereo>stereo</stereo>
</audio>
<category>Basketball</category>
<icon src="https://api.ppvs.su/assets/thumb/041680b85c75266d09149d55f61d8217-thumbnail.jpg" />
</programme>

<channel id="ppv-13082">
<display-name>UFC Fight Night: Garcia vs. Onama</display-name>
</channel>
<programme
start="20251101200000 +0000"
stop="20251102040000 +0000"
channel="ppv-13082"
>
<title lang="en">UFC Fight Night: Garcia vs. Onama</title>
<sub-title>Combat Sports</sub-title>
<video>
<present>yes</present>
<colour>yes</colour>
</video>
<audio>
<present>yes</present>
<stereo>stereo</stereo>
</audio>
<category>Combat Sports</category>
<icon src="https://api.ppvs.su/assets/thumb/31c850d2a0df715f1d69a1ccb280fbdd-thumbnail.jpg" />
</programme>

<channel id="ppv-13031">
<display-name>OKTAGON 79 - Deutsch</display-name>
</channel>
<programme
start="20251101170000 +0000"
stop="20251101230000 +0000"
channel="ppv-13031"
>
<title lang="en">OKTAGON 79 - Deutsch</title>
<sub-title>Combat Sports</sub-title>
<video>
<present>yes</present>
<colour>yes</colour>
</video>
<audio>
<present>yes</present>
<stereo>stereo</stereo>
</audio>
<category>Combat Sports</category>
<icon src="https://api.ppvs.su/assets/thumb/2075f89796c876f2c14be1f853c858d3-thumbnail.jpg" />
</programme>

<channel id="ppv-13032">
<display-name>OKTAGON 79 - English</display-name>
</channel>
<programme
start="20251101170000 +0000"
stop="20251101230000 +0000"
channel="ppv-13032"
>
<title lang="en">OKTAGON 79 - English</title>
<sub-title>Combat Sports</sub-title>
<video>
<present>yes</present>
<colour>yes</colour>
</video>
<audio>
<present>yes</present>
<stereo>stereo</stereo>
</audio>
<category>Combat Sports</category>
<icon src="https://api.ppvs.su/assets/thumb/2075f89796c876f2c14be1f853c858d3-thumbnail.jpg" />
</programme>

<channel id="ppv-13033">
<display-name>OKTAGON 79 - Czech</display-name>
</channel>
<programme
start="20251101170000 +0000"
stop="20251101230000 +0000"
channel="ppv-13033"
>
<title lang="en">OKTAGON 79 - Czech</title>
<sub-title>Combat Sports</sub-title>
<video>
<present>yes</present>
<colour>yes</colour>
</video>
<audio>
<present>yes</present>
<stereo>stereo</stereo>
</audio>
<category>Combat Sports</category>
<icon src="https://api.ppvs.su/assets/thumb/2075f89796c876f2c14be1f853c858d3-thumbnail.jpg" />
</programme>

<channel id="ppv-12894">
<display-name>Sunderland vs. Everton</display-name>
</channel>
<programme
start="20251103200000 +0000"
stop="20251103223000 +0000"
channel="ppv-12894"
>
<title lang="en">Sunderland vs. Everton</title>
<sub-title>Football</sub-title>
<video>
<present>yes</present>
<colour>yes</colour>
</video>
<audio>
<present>yes</present>
<stereo>stereo</stereo>
</audio>
<category>Football</category>
<icon src="https://api.ppvs.su/assets/thumb/bce788f473abc7c8be239c78647b613f-thumbnail.jpg" />
</programme>

<channel id="ppv-12981">
<display-name>Real Oviedo vs. CA Osasuna</display-name>
</channel>
<programme
start="20251103200000 +0000"
stop="20251103223000 +0000"
channel="ppv-12981"
>
<title lang="en">Real Oviedo vs. CA Osasuna</title>
<sub-title>Football</sub-title>
<video>
<present>yes</present>
<colour>yes</colour>
</video>
<audio>
<present>yes</present>
<stereo>stereo</stereo>
</audio>
<category>Football</category>
<icon src="https://api.ppvs.su/assets/thumb/189e9b995f759864d3e69988f93e5ce2-thumbnail.jpg" />
</programme>

<channel id="ppv-13044">
<display-name>Lazio vs. Cagliari</display-name>
</channel>
<programme
start="20251103194500 +0000"
stop="20251103221500 +0000"
channel="ppv-13044"
>
<title lang="en">Lazio vs. Cagliari</title>
<sub-title>Football</sub-title>
<video>
<present>yes</present>
<colour>yes</colour>
</video>
<audio>
<present>yes</present>
<stereo>stereo</stereo>
</audio>
<category>Football</category>
<icon src="https://api.ppvs.su/assets/thumb/5c4c389d06896d554e9a13710e5696c2-thumbnail.jpg" />
</programme>

<channel id="ppv-13043">
<display-name>Sassuolo vs. Genoa</display-name>
</channel>
<programme
start="20251103173000 +0000"
stop="20251103200000 +0000"
channel="ppv-13043"
>
<title lang="en">Sassuolo vs. Genoa</title>
<sub-title>Football</sub-title>
<video>
<present>yes</present>
<colour>yes</colour>
</video>
<audio>
<present>yes</present>
<stereo>stereo</stereo>
</audio>
<category>Football</category>
<icon src="https://api.ppvs.su/assets/thumb/71ddfde91ecbc9abf80f6db3d5a786a1-thumbnail.jpg" />
</programme>

<channel id="ppv-12980">
<display-name>Real Betis vs. RCD Mallorca</display-name>
</channel>
<programme
start="20251102200000 +0000"
stop="20251102223000 +0000"
channel="ppv-12980"
>
<title lang="en">Real Betis vs. RCD Mallorca</title>
<sub-title>Football</sub-title>
<video>
<present>yes</present>
<colour>yes</colour>
</video>
<audio>
<present>yes</present>
<stereo>stereo</stereo>
</audio>
<category>Football</category>
<icon src="https://api.ppvs.su/assets/thumb/056a125115253149a46687986a45f450-thumbnail.jpg" />
</programme>

<channel id="ppv-12857">
<display-name>Brest vs. OL</display-name>
</channel>
<programme
start="20251102194500 +0000"
stop="20251102221500 +0000"
channel="ppv-12857"
>
<title lang="en">Brest vs. OL</title>
<sub-title>Football</sub-title>
<video>
<present>yes</present>
<colour>yes</colour>
</video>
<audio>
<present>yes</present>
<stereo>stereo</stereo>
</audio>
<category>Football</category>
<icon src="https://api.ppvs.su/assets/thumb/820d9b3191bd3e9af11496ed88800d98-thumbnail.jpg" />
</programme>

<channel id="ppv-13042">
<display-name>Milan vs. Roma</display-name>
</channel>
<programme
start="20251102194500 +0000"
stop="20251102221500 +0000"
channel="ppv-13042"
>
<title lang="en">Milan vs. Roma</title>
<sub-title>Football</sub-title>
<video>
<present>yes</present>
<colour>yes</colour>
</video>
<audio>
<present>yes</present>
<stereo>stereo</stereo>
</audio>
<category>Football</category>
<icon src="https://api.ppvs.su/assets/thumb/7f944524bbfc171e5c09c27b4a2635ca-thumbnail.jpg" />
</programme>

<channel id="ppv-12979">
<display-name>FC Barcelona vs. Elche CF</display-name>
</channel>
<programme
start="20251102173000 +0000"
stop="20251102200000 +0000"
channel="ppv-12979"
>
<title lang="en">FC Barcelona vs. Elche CF</title>
<sub-title>Football</sub-title>
<video>
<present>yes</present>
<colour>yes</colour>
</video>
<audio>
<present>yes</present>
<stereo>stereo</stereo>
</audio>
<category>Football</category>
<icon src="https://api.ppvs.su/assets/thumb/9146ebfdd0d769244b7ca20c3b97f44f-thumbnail.jpg" />
</programme>

<channel id="ppv-13041">
<display-name>Parma vs. Bologna</display-name>
</channel>
<programme
start="20251102170000 +0000"
stop="20251102193000 +0000"
channel="ppv-13041"
>
<title lang="en">Parma vs. Bologna</title>
<sub-title>Football</sub-title>
<video>
<present>yes</present>
<colour>yes</colour>
</video>
<audio>
<present>yes</present>
<stereo>stereo</stereo>
</audio>
<category>Football</category>
<icon src="https://api.ppvs.su/assets/thumb/8da5ff3441cb3bb43b6d22aa66fefacd-thumbnail.jpg" />
</programme>

<channel id="ppv-12892">
<display-name>Manchester City vs. Bournemouth</display-name>
</channel>
<programme
start="20251102163000 +0000"
stop="20251102190000 +0000"
channel="ppv-12892"
>
<title lang="en">Manchester City vs. Bournemouth</title>
<sub-title>Football</sub-title>
<video>
<present>yes</present>
<colour>yes</colour>
</video>
<audio>
<present>yes</present>
<stereo>stereo</stereo>
</audio>
<category>Football</category>
<icon src="https://api.ppvs.su/assets/thumb/070294766760d338467edcfbaf00c443-thumbnail.jpg" />
</programme>

<channel id="ppv-12905">
<display-name>Wolfsburg vs. Hoffenheim</display-name>
</channel>
<programme
start="20251102163000 +0000"
stop="20251102190000 +0000"
channel="ppv-12905"
>
<title lang="en">Wolfsburg vs. Hoffenheim</title>
<sub-title>Football</sub-title>
<video>
<present>yes</present>
<colour>yes</colour>
</video>
<audio>
<present>yes</present>
<stereo>stereo</stereo>
</audio>
<category>Football</category>
<icon src="https://api.ppvs.su/assets/thumb/ea642cfeeca0f127eb21488a8c15b9ce-thumbnail.jpg" />
</programme>

<channel id="ppv-12858">
<display-name>RC Lens vs. FC Lorient</display-name>
</channel>
<programme
start="20251102161500 +0000"
stop="20251102184500 +0000"
channel="ppv-12858"
>
<title lang="en">RC Lens vs. FC Lorient</title>
<sub-title>Football</sub-title>
<video>
<present>yes</present>
<colour>yes</colour>
</video>
<audio>
<present>yes</present>
<stereo>stereo</stereo>
</audio>
<category>Football</category>
<icon src="https://api.ppvs.su/assets/thumb/3fe4399191722b32cca4408380f99d5b-thumbnail.jpg" />
</programme>

<channel id="ppv-12859">
<display-name>LOSC vs. Angers SCO</display-name>
</channel>
<programme
start="20251102161500 +0000"
stop="20251102184500 +0000"
channel="ppv-12859"
>
<title lang="en">LOSC vs. Angers SCO</title>
<sub-title>Football</sub-title>
<video>
<present>yes</present>
<colour>yes</colour>
</video>
<audio>
<present>yes</present>
<stereo>stereo</stereo>
</audio>
<category>Football</category>
<icon src="https://api.ppvs.su/assets/thumb/e545fcca7e87df4a5768c3ee1a4d36ca-thumbnail.jpg" />
</programme>

<channel id="ppv-12860">
<display-name>FC Nantes vs. FC Metz</display-name>
</channel>
<programme
start="20251102161500 +0000"
stop="20251102184500 +0000"
channel="ppv-12860"
>
<title lang="en">FC Nantes vs. FC Metz</title>
<sub-title>Football</sub-title>
<video>
<present>yes</present>
<colour>yes</colour>
</video>
<audio>
<present>yes</present>
<stereo>stereo</stereo>
</audio>
<category>Football</category>
<icon src="https://api.ppvs.su/assets/thumb/ba24a9a558fd0694c621be1ea04cf3d6-thumbnail.jpg" />
</programme>

<channel id="ppv-12862">
<display-name>Toulouse FC vs. Havre AC</display-name>
</channel>
<programme
start="20251102161500 +0000"
stop="20251102184500 +0000"
channel="ppv-12862"
>
<title lang="en">Toulouse FC vs. Havre AC</title>
<sub-title>Football</sub-title>
<video>
<present>yes</present>
<colour>yes</colour>
</video>
<audio>
<present>yes</present>
<stereo>stereo</stereo>
</audio>
<category>Football</category>
<icon src="https://api.ppvs.su/assets/thumb/c076361fbc70da9959eb82b8f9181a97-thumbnail.jpg" />
</programme>

<channel id="ppv-12978">
<display-name>Deportivo Alavés vs. RCD Espanyol de Barcelona</display-name>
</channel>
<programme
start="20251102151500 +0000"
stop="20251102174500 +0000"
channel="ppv-12978"
>
<title lang="en">Deportivo Alavés vs. RCD Espanyol de Barcelona</title>
<sub-title>Football</sub-title>
<video>
<present>yes</present>
<colour>yes</colour>
</video>
<audio>
<present>yes</present>
<stereo>stereo</stereo>
</audio>
<category>Football</category>
<icon src="https://api.ppvs.su/assets/thumb/c3d2e3b55816a6664c3924705132a6b3-thumbnail.jpg" />
</programme>

<channel id="ppv-12904">
<display-name>Cologne vs. Hamburg</display-name>
</channel>
<programme
start="20251102143000 +0000"
stop="20251102170000 +0000"
channel="ppv-12904"
>
<title lang="en">Cologne vs. Hamburg</title>
<sub-title>Football</sub-title>
<video>
<present>yes</present>
<colour>yes</colour>
</video>
<audio>
<present>yes</present>
<stereo>stereo</stereo>
</audio>
<category>Football</category>
<icon src="https://api.ppvs.su/assets/thumb/8e79139d844b8d45007de08833617c7b-thumbnail.jpg" />
</programme>

<channel id="ppv-12861">
<display-name>Rennes vs. Strasbourg</display-name>
</channel>
<programme
start="20251102140000 +0000"
stop="20251102163000 +0000"
channel="ppv-12861"
>
<title lang="en">Rennes vs. Strasbourg</title>
<sub-title>Football</sub-title>
<video>
<present>yes</present>
<colour>yes</colour>
</video>
<audio>
<present>yes</present>
<stereo>stereo</stereo>
</audio>
<category>Football</category>
<icon src="https://api.ppvs.su/assets/thumb/8a61f6d5976c5dc7c13af0b7050a5e9b-thumbnail.jpg" />
</programme>

<channel id="ppv-12896">
<display-name>West Ham United vs. Newcastle United</display-name>
</channel>
<programme
start="20251102140000 +0000"
stop="20251102163000 +0000"
channel="ppv-12896"
>
<title lang="en">West Ham United vs. Newcastle United</title>
<sub-title>Football</sub-title>
<video>
<present>yes</present>
<colour>yes</colour>
</video>
<audio>
<present>yes</present>
<stereo>stereo</stereo>
</audio>
<category>Football</category>
<icon src="https://api.ppvs.su/assets/thumb/5831a8b092bcd668f175cf89e8422d54-thumbnail.jpg" />
</programme>

<channel id="ppv-13039">
<display-name>Fiorentina vs. Lecce</display-name>
</channel>
<programme
start="20251102140000 +0000"
stop="20251102163000 +0000"
channel="ppv-13039"
>
<title lang="en">Fiorentina vs. Lecce</title>
<sub-title>Football</sub-title>
<video>
<present>yes</present>
<colour>yes</colour>
</video>
<audio>
<present>yes</present>
<stereo>stereo</stereo>
</audio>
<category>Football</category>
<icon src="https://api.ppvs.su/assets/thumb/b8af139e912fe513f54cf797c5d5fad3-thumbnail.jpg" />
</programme>

<channel id="ppv-13040">
<display-name>Torino vs. Pisa</display-name>
</channel>
<programme
start="20251102140000 +0000"
stop="20251102163000 +0000"
channel="ppv-13040"
>
<title lang="en">Torino vs. Pisa</title>
<sub-title>Football</sub-title>
<video>
<present>yes</present>
<colour>yes</colour>
</video>
<audio>
<present>yes</present>
<stereo>stereo</stereo>
</audio>
<category>Football</category>
<icon src="https://api.ppvs.su/assets/thumb/e507dcaebb88ea74c612098108a47073-thumbnail.jpg" />
</programme>

<channel id="ppv-12977">
<display-name>Levante UD vs. Celta</display-name>
</channel>
<programme
start="20251102130000 +0000"
stop="20251102153000 +0000"
channel="ppv-12977"
>
<title lang="en">Levante UD vs. Celta</title>
<sub-title>Football</sub-title>
<video>
<present>yes</present>
<colour>yes</colour>
</video>
<audio>
<present>yes</present>
<stereo>stereo</stereo>
</audio>
<category>Football</category>
<icon src="https://api.ppvs.su/assets/thumb/c73eed78ae029a8084603fdb99cefd33-thumbnail.jpg" />
</programme>

<channel id="ppv-13038">
<display-name>Hellas Verona vs. Inter</display-name>
</channel>
<programme
start="20251102113000 +0000"
stop="20251102140000 +0000"
channel="ppv-13038"
>
<title lang="en">Hellas Verona vs. Inter</title>
<sub-title>Football</sub-title>
<video>
<present>yes</present>
<colour>yes</colour>
</video>
<audio>
<present>yes</present>
<stereo>stereo</stereo>
</audio>
<category>Football</category>
<icon src="https://api.ppvs.su/assets/thumb/462c452909510e7122827433726d3a4b-thumbnail.jpg" />
</programme>

<channel id="ppv-12854">
<display-name>AJ Auxerre vs. OM</display-name>
</channel>
<programme
start="20251101200500 +0000"
stop="20251101223500 +0000"
channel="ppv-12854"
>
<title lang="en">AJ Auxerre vs. OM</title>
<sub-title>Football</sub-title>
<video>
<present>yes</present>
<colour>yes</colour>
</video>
<audio>
<present>yes</present>
<stereo>stereo</stereo>
</audio>
<category>Football</category>
<icon src="https://api.ppvs.su/assets/thumb/b3066133aedb963aebfb1e59c3d31549-thumbnail.jpg" />
</programme>

<channel id="ppv-12891">
<display-name>Liverpool vs. Aston Villa</display-name>
</channel>
<programme
start="20251101200000 +0000"
stop="20251101223000 +0000"
channel="ppv-12891"
>
<title lang="en">Liverpool vs. Aston Villa</title>
<sub-title>Football</sub-title>
<video>
<present>yes</present>
<colour>yes</colour>
</video>
<audio>
<present>yes</present>
<stereo>stereo</stereo>
</audio>
<category>Football</category>
<icon src="https://api.ppvs.su/assets/thumb/da64b16cd0084624098a70c0070d44d9-thumbnail.jpg" />
</programme>

<channel id="ppv-12976">
<display-name>Real Madrid vs. Valencia CF</display-name>
</channel>
<programme
start="20251101200000 +0000"
stop="20251101223000 +0000"
channel="ppv-12976"
>
<title lang="en">Real Madrid vs. Valencia CF</title>
<sub-title>Football</sub-title>
<video>
<present>yes</present>
<colour>yes</colour>
</video>
<audio>
<present>yes</present>
<stereo>stereo</stereo>
</audio>
<category>Football</category>
<icon src="https://api.ppvs.su/assets/thumb/8905dfd747e99e4852659989e6102698-thumbnail.jpg" />
</programme>

<channel id="ppv-13037">
<display-name>Cremonese vs. Juventus</display-name>
</channel>
<programme
start="20251101194500 +0000"
stop="20251101221500 +0000"
channel="ppv-13037"
>
<title lang="en">Cremonese vs. Juventus</title>
<sub-title>Football</sub-title>
<video>
<present>yes</present>
<colour>yes</colour>
</video>
<audio>
<present>yes</present>
<stereo>stereo</stereo>
</audio>
<category>Football</category>
<icon src="https://api.ppvs.su/assets/thumb/7d27b923ce1048700fd36c69a3ab3212-thumbnail.jpg" />
</programme>

<channel id="ppv-13080">
<display-name>Chicago Blackhawks vs. Edmonton Oilers</display-name>
</channel>
<programme
start="20251102030000 +0000"
stop="20251102060000 +0000"
channel="ppv-13080"
>
<title lang="en">Chicago Blackhawks vs. Edmonton Oilers</title>
<sub-title>Ice Hockey</sub-title>
<video>
<present>yes</present>
<colour>yes</colour>
</video>
<audio>
<present>yes</present>
<stereo>stereo</stereo>
</audio>
<category>Ice Hockey</category>
<icon src="https://api.ppvs.su/assets/thumb/2b00c89635e53c117a8c99a02c0ebffb-thumbnail.jpg" />
</programme>

<channel id="ppv-13081">
<display-name>New York Rangers vs. Seattle Kraken</display-name>
</channel>
<programme
start="20251102030000 +0000"
stop="20251102060000 +0000"
channel="ppv-13081"
>
<title lang="en">New York Rangers vs. Seattle Kraken</title>
<sub-title>Ice Hockey</sub-title>
<video>
<present>yes</present>
<colour>yes</colour>
</video>
<audio>
<present>yes</present>
<stereo>stereo</stereo>
</audio>
<category>Ice Hockey</category>
<icon src="https://api.ppvs.su/assets/thumb/c5049398c514c3107c67fd26ae5447d2-thumbnail.jpg" />
</programme>

<channel id="ppv-13079">
<display-name>New Jersey Devils vs. Los Angeles Kings</display-name>
</channel>
<programme
start="20251102020000 +0000"
stop="20251102050000 +0000"
channel="ppv-13079"
>
<title lang="en">New Jersey Devils vs. Los Angeles Kings</title>
<sub-title>Ice Hockey</sub-title>
<video>
<present>yes</present>
<colour>yes</colour>
</video>
<audio>
<present>yes</present>
<stereo>stereo</stereo>
</audio>
<category>Ice Hockey</category>
<icon src="https://api.ppvs.su/assets/thumb/c0d8966e0b50b5dc6170072245d9534e-thumbnail.jpg" />
</programme>

<channel id="ppv-13074">
<display-name>Washington Capitals vs. Buffalo Sabres</display-name>
</channel>
<programme
start="20251101230000 +0000"
stop="20251102020000 +0000"
channel="ppv-13074"
>
<title lang="en">Washington Capitals vs. Buffalo Sabres</title>
<sub-title>Ice Hockey</sub-title>
<video>
<present>yes</present>
<colour>yes</colour>
</video>
<audio>
<present>yes</present>
<stereo>stereo</stereo>
</audio>
<category>Ice Hockey</category>
<icon src="https://api.ppvs.su/assets/thumb/e5e59468ff913f7b805e9f8039dce217-thumbnail.jpg" />
</programme>

<channel id="ppv-13075">
<display-name>Ottawa Senators vs. Montreal Canadiens</display-name>
</channel>
<programme
start="20251101230000 +0000"
stop="20251102020000 +0000"
channel="ppv-13075"
>
<title lang="en">Ottawa Senators vs. Montreal Canadiens</title>
<sub-title>Ice Hockey</sub-title>
<video>
<present>yes</present>
<colour>yes</colour>
</video>
<audio>
<present>yes</present>
<stereo>stereo</stereo>
</audio>
<category>Ice Hockey</category>
<icon src="https://api.ppvs.su/assets/thumb/bc5cc968803cb153e6468b7205ce68ce-thumbnail.jpg" />
</programme>

<channel id="ppv-13076">
<display-name>Toronto Maple Leafs vs. Philadelphia Flyers</display-name>
</channel>
<programme
start="20251101230000 +0000"
stop="20251102020000 +0000"
channel="ppv-13076"
>
<title lang="en">Toronto Maple Leafs vs. Philadelphia Flyers</title>
<sub-title>Ice Hockey</sub-title>
<video>
<present>yes</present>
<colour>yes</colour>
</video>
<audio>
<present>yes</present>
<stereo>stereo</stereo>
</audio>
<category>Ice Hockey</category>
<icon src="https://api.ppvs.su/assets/thumb/13b189c8cc6c75486e313d997ada80f6-thumbnail.jpg" />
</programme>

<channel id="ppv-13077">
<display-name>St. Louis Blues vs. Columbus Blue Jackets</display-name>
</channel>
<programme
start="20251101230000 +0000"
stop="20251102020000 +0000"
channel="ppv-13077"
>
<title lang="en">St. Louis Blues vs. Columbus Blue Jackets</title>
<sub-title>Ice Hockey</sub-title>
<video>
<present>yes</present>
<colour>yes</colour>
</video>
<audio>
<present>yes</present>
<stereo>stereo</stereo>
</audio>
<category>Ice Hockey</category>
<icon src="https://api.ppvs.su/assets/thumb/fc2edaf53e04877718d1dbb4ef3b13cc-thumbnail.jpg" />
</programme>

<channel id="ppv-13078">
<display-name>Vancouver Canucks vs. Minnesota Wild</display-name>
</channel>
<programme
start="20251101230000 +0000"
stop="20251102020000 +0000"
channel="ppv-13078"
>
<title lang="en">Vancouver Canucks vs. Minnesota Wild</title>
<sub-title>Ice Hockey</sub-title>
<video>
<present>yes</present>
<colour>yes</colour>
</video>
<audio>
<present>yes</present>
<stereo>stereo</stereo>
</audio>
<category>Ice Hockey</category>
<icon src="https://api.ppvs.su/assets/thumb/9ba8ac99fdd141f1d803eb78ac2305f7-thumbnail.jpg" />
</programme>

<channel id="ppv-13073">
<display-name>Dallas Stars vs. Florida Panthers</display-name>
</channel>
<programme
start="20251101220000 +0000"
stop="20251102010000 +0000"
channel="ppv-13073"
>
<title lang="en">Dallas Stars vs. Florida Panthers</title>
<sub-title>Ice Hockey</sub-title>
<video>
<present>yes</present>
<colour>yes</colour>
</video>
<audio>
<present>yes</present>
<stereo>stereo</stereo>
</audio>
<category>Ice Hockey</category>
<icon src="https://api.ppvs.su/assets/thumb/311bab5ac5914961f20d3cce40bb0b0f-thumbnail.jpg" />
</programme>

<channel id="ppv-13072">
<display-name>Colorado Avalanche vs. San Jose Sharks</display-name>
</channel>
<programme
start="20251101200000 +0000"
stop="20251101230000 +0000"
channel="ppv-13072"
>
<title lang="en">Colorado Avalanche vs. San Jose Sharks</title>
<sub-title>Ice Hockey</sub-title>
<video>
<present>yes</present>
<colour>yes</colour>
</video>
<audio>
<present>yes</present>
<stereo>stereo</stereo>
</audio>
<category>Ice Hockey</category>
<icon src="https://api.ppvs.su/assets/thumb/54e4aa2a96f0c0ec03e0c6107361f499-thumbnail.jpg" />
</programme>

<channel id="ppv-13071">
<display-name>Calgary Flames vs. Nashville Predators</display-name>
</channel>
<programme
start="20251101193000 +0000"
stop="20251101223000 +0000"
channel="ppv-13071"
>
<title lang="en">Calgary Flames vs. Nashville Predators</title>
<sub-title>Ice Hockey</sub-title>
<video>
<present>yes</present>
<colour>yes</colour>
</video>
<audio>
<present>yes</present>
<stereo>stereo</stereo>
</audio>
<category>Ice Hockey</category>
<icon src="https://api.ppvs.su/assets/thumb/e84aceadaa09a635e04f97bdd45325b6-thumbnail.jpg" />
</programme>

<channel id="ppv-12886">
<display-name>AEW: Saturday Night Collision</display-name>
</channel>
<programme
start="20251102000000 +0000"
stop="20251102030000 +0000"
channel="ppv-12886"
>
<title lang="en">AEW: Saturday Night Collision</title>
<sub-title>Wrestling</sub-title>
<video>
<present>yes</present>
<colour>yes</colour>
</video>
<audio>
<present>yes</present>
<stereo>stereo</stereo>
</audio>
<category>Wrestling</category>
<icon src="https://api.ppvs.su/assets/thumb/6e29b1bb679dd5133c85bbaadc2c4b13-thumbnail.jpg" />
</programme>
</tv>